enclosed/__init__.py
enclosed/__main__.py
enclosed/parser.py
enclosed/version.py
tests/test_parser_fail.py
tests/test_parser_success.py
tests/test_version.py
enclosed-0.0.3.dist-info/LICENSE
enclosed-0.0.3.dist-info/METADATA
enclosed-0.0.3.dist-info/WHEEL
enclosed-0.0.3.dist-info/entry_points.txt
enclosed-0.0.3.dist-info/top_level.txt
enclosed-0.0.3.dist-info/RECORD
