Metadata-Version: 2.1
Name: enclosed
Version: 0.0.3
Summary: Extract strings enclosed by symbol
Home-page: https://github.com/joaompinto/enclosed
Author: João Pinto
Author-email: lamego.pinto@gmail.com
License: MIT
Platform: UNKNOWN
Classifier: Development Status :: 5 - Production/Stable
Classifier: Environment :: Console
Classifier: Intended Audience :: Developers
Classifier: Intended Audience :: Information Technology
Classifier: License :: OSI Approved :: MIT License
Classifier: Operating System :: OS Independent
Classifier: Programming Language :: Python
Classifier: Programming Language :: Python :: 3 :: Only
Classifier: Programming Language :: Python :: 3.6
Classifier: Programming Language :: Python :: 3.8
Classifier: Programming Language :: Python :: 3.10
License-File: LICENSE
